{
  "ticker": "IP",
  "as_of_date": "2026-04-21",
  "close": 35.44,
  "sma_20": 36.0265,
  "sma_50": 39.6156,
  "sma_200": 42.5509,
  "ema_20": 36.5201,
  "rsi_14": 48.329,
  "macd_line": -0.5509,
  "macd_signal": -0.8264,
  "macd_histogram": 0.2755,
  "bb_upper": 37.6089,
  "bb_middle": 36.0265,
  "bb_lower": 34.4441,
  "bb_pct": 0.3147,
  "atr_14": 1.1936,
  "volume": 4254609,
  "volume_sma_20": 6443660.45,
  "volume_ratio": 0.6603,
  "high_52w": 54.3642,
  "low_52w": 33.57,
  "pct_from_52w_high": -0.3481,
  "pct_from_52w_low": 0.0557,
  "above_sma_20": false,
  "above_sma_50": false,
  "above_sma_200": false
}