{
  "ticker": "NXPI",
  "as_of_date": "2026-04-17",
  "close": 216.03,
  "sma_20": 200.114,
  "sma_50": 211.0682,
  "sma_200": 217.4395,
  "ema_20": 204.5118,
  "rsi_14": 77.0477,
  "macd_line": 1.7263,
  "macd_signal": -1.3266,
  "macd_histogram": 3.0529,
  "bb_upper": 216.4755,
  "bb_middle": 200.114,
  "bb_lower": 183.7525,
  "bb_pct": 0.9864,
  "atr_14": 7.0407,
  "volume": 4287800,
  "volume_sma_20": 2824380.0,
  "volume_ratio": 1.5181,
  "high_52w": 255.0364,
  "low_52w": 163.4836,
  "pct_from_52w_high": -0.1529,
  "pct_from_52w_low": 0.3214,
  "above_sma_20": true,
  "above_sma_50": true,
  "above_sma_200": false
}