{
  "info": {
    "symbol": "UAL",
    "name": "United Airlines Holdings, Inc.",
    "sector": "Industrials",
    "industry": "Airlines",
    "market": "US",
    "currency": "USD",
    "market_cap": 31533193216.0,
    "pe_ratio": 9.522549,
    "forward_pe": 6.760039,
    "dividend_yield": null,
    "beta": 1.286,
    "fifty_two_week_high": 119.21,
    "fifty_two_week_low": 65.26
  },
  "financials": {
    "revenue": 59070000000.0,
    "net_income": 3353000000.0,
    "total_debt": 31036000000.0,
    "total_equity": 15282000000.0,
    "free_cash_flow": 2557000000.0,
    "gross_margin": 0.2877941425427459,
    "operating_margin": 0.08417132216014897,
    "net_margin": 0.05676316234975453
  },
  "analyst_recommendations": [
    {
      "index": 0,
      "period": "0m",
      "strongBuy": 5,
      "buy": 19,
      "hold": 2,
      "sell": 0,
      "strongSell": 0
    },
    {
      "index": 1,
      "period": "-1m",
      "strongBuy": 5,
      "buy": 19,
      "hold": 2,
      "sell": 0,
      "strongSell": 0
    },
    {
      "index": 2,
      "period": "-2m",
      "strongBuy": 5,
      "buy": 19,
      "hold": 2,
      "sell": 0,
      "strongSell": 0
    },
    {
      "index": 3,
      "period": "-3m",
      "strongBuy": 5,
      "buy": 19,
      "hold": 2,
      "sell": 0,
      "strongSell": 0
    }
  ],
  "news_headlines": [
    {
      "title": "",
      "link": "",
      "publisher": ""
    },
    {
      "title": "",
      "link": "",
      "publisher": ""
    },
    {
      "title": "",
      "link": "",
      "publisher": ""
    },
    {
      "title": "",
      "link": "",
      "publisher": ""
    },
    {
      "title": "",
      "link": "",
      "publisher": ""
    },
    {
      "title": "",
      "link": "",
      "publisher": ""
    },
    {
      "title": "",
      "link": "",
      "publisher": ""
    },
    {
      "title": "",
      "link": "",
      "publisher": ""
    },
    {
      "title": "",
      "link": "",
      "publisher": ""
    },
    {
      "title": "",
      "link": "",
      "publisher": ""
    }
  ],
  "fetched_at": "2026-04-21T23:15:55.484577"
}