{
  "info": {
    "symbol": "TTWO",
    "name": "Take-Two Interactive Software, ",
    "sector": "Communication Services",
    "industry": "Electronic Gaming & Multimedia",
    "market": "US",
    "currency": "USD",
    "market_cap": 40303435776.0,
    "pe_ratio": null,
    "forward_pe": 27.622835,
    "dividend_yield": null,
    "beta": 0.965,
    "fifty_two_week_high": 264.79,
    "fifty_two_week_low": 187.63
  },
  "financials": {
    "revenue": 5633600000.0,
    "net_income": -4478900000.0,
    "total_debt": 4105900000.0,
    "total_equity": 2137700000.0,
    "free_cash_flow": -214600000.0,
    "gross_margin": 0.5435600681624538,
    "operating_margin": -0.1312482249360977,
    "net_margin": -0.7950333712013633
  },
  "analyst_recommendations": [
    {
      "index": 0,
      "period": "0m",
      "strongBuy": 2,
      "buy": 24,
      "hold": 1,
      "sell": 0,
      "strongSell": 1
    },
    {
      "index": 1,
      "period": "-1m",
      "strongBuy": 2,
      "buy": 24,
      "hold": 1,
      "sell": 0,
      "strongSell": 1
    },
    {
      "index": 2,
      "period": "-2m",
      "strongBuy": 2,
      "buy": 24,
      "hold": 1,
      "sell": 0,
      "strongSell": 1
    },
    {
      "index": 3,
      "period": "-3m",
      "strongBuy": 3,
      "buy": 24,
      "hold": 1,
      "sell": 1,
      "strongSell": 0
    }
  ],
  "news_headlines": [
    {
      "title": "",
      "link": "",
      "publisher": ""
    },
    {
      "title": "",
      "link": "",
      "publisher": ""
    },
    {
      "title": "",
      "link": "",
      "publisher": ""
    },
    {
      "title": "",
      "link": "",
      "publisher": ""
    },
    {
      "title": "",
      "link": "",
      "publisher": ""
    },
    {
      "title": "",
      "link": "",
      "publisher": ""
    },
    {
      "title": "",
      "link": "",
      "publisher": ""
    },
    {
      "title": "",
      "link": "",
      "publisher": ""
    },
    {
      "title": "",
      "link": "",
      "publisher": ""
    },
    {
      "title": "",
      "link": "",
      "publisher": ""
    }
  ],
  "fetched_at": "2026-04-21T23:15:50.491117"
}