{
  "ticker": "NKE",
  "as_of_date": "2026-04-21",
  "close": 46.39,
  "sma_20": 46.8205,
  "sma_50": 54.261,
  "sma_200": 64.504,
  "ema_20": 47.2483,
  "rsi_14": 30.8289,
  "macd_line": -2.5074,
  "macd_signal": -3.1597,
  "macd_histogram": 0.6522,
  "bb_upper": 54.6103,
  "bb_middle": 46.8205,
  "bb_lower": 39.0307,
  "bb_pct": 0.4724,
  "atr_14": 1.7836,
  "volume": 17351807,
  "volume_sma_20": 29675465.35,
  "volume_ratio": 0.5847,
  "high_52w": 78.727,
  "low_52w": 42.09,
  "pct_from_52w_high": -0.4107,
  "pct_from_52w_low": 0.1022,
  "above_sma_20": false,
  "above_sma_50": false,
  "above_sma_200": false
}