{
  "info": {
    "symbol": "SHW",
    "name": "Sherwin-Williams Company (The)",
    "sector": "Basic Materials",
    "industry": "Specialty Chemicals",
    "market": "US",
    "currency": "USD",
    "market_cap": 82907914240.0,
    "pe_ratio": 32.64488,
    "forward_pe": 25.028908,
    "dividend_yield": 0.93,
    "beta": 1.269,
    "fifty_two_week_high": 379.65,
    "fifty_two_week_low": 301.58
  },
  "financials": {
    "revenue": 23574300000.0,
    "net_income": 2568500000.0,
    "total_debt": 12942600000.0,
    "total_equity": 4598300000.0,
    "free_cash_flow": 2654000000.0,
    "gross_margin": 0.48847685827362847,
    "operating_margin": 0.16105250208913943,
    "net_margin": 0.1089533941622869
  },
  "analyst_recommendations": [
    {
      "index": 0,
      "period": "0m",
      "strongBuy": 3,
      "buy": 12,
      "hold": 9,
      "sell": 1,
      "strongSell": 0
    },
    {
      "index": 1,
      "period": "-1m",
      "strongBuy": 3,
      "buy": 13,
      "hold": 9,
      "sell": 1,
      "strongSell": 0
    },
    {
      "index": 2,
      "period": "-2m",
      "strongBuy": 3,
      "buy": 13,
      "hold": 10,
      "sell": 1,
      "strongSell": 0
    },
    {
      "index": 3,
      "period": "-3m",
      "strongBuy": 3,
      "buy": 13,
      "hold": 10,
      "sell": 0,
      "strongSell": 1
    }
  ],
  "news_headlines": [
    {
      "title": "",
      "link": "",
      "publisher": ""
    },
    {
      "title": "",
      "link": "",
      "publisher": ""
    },
    {
      "title": "",
      "link": "",
      "publisher": ""
    },
    {
      "title": "",
      "link": "",
      "publisher": ""
    },
    {
      "title": "",
      "link": "",
      "publisher": ""
    },
    {
      "title": "",
      "link": "",
      "publisher": ""
    },
    {
      "title": "",
      "link": "",
      "publisher": ""
    },
    {
      "title": "",
      "link": "",
      "publisher": ""
    },
    {
      "title": "",
      "link": "",
      "publisher": ""
    },
    {
      "title": "",
      "link": "",
      "publisher": ""
    }
  ],
  "fetched_at": "2026-04-21T23:14:49.822271"
}