{
  "info": {
    "symbol": "SMCI",
    "name": "Super Micro Computer, Inc.",
    "sector": "Technology",
    "industry": "Computer Hardware",
    "market": "US",
    "currency": "USD",
    "market_cap": 17149763584.0,
    "pe_ratio": 20.846714,
    "forward_pe": 9.560152,
    "dividend_yield": null,
    "beta": 1.629,
    "fifty_two_week_high": 62.36,
    "fifty_two_week_low": 19.48
  },
  "financials": {
    "revenue": 21972042000.0,
    "net_income": 1048854000.0,
    "total_debt": 4778842000.0,
    "total_equity": 6301693000.0,
    "free_cash_flow": 1532310000.0,
    "gross_margin": 0.11059154174200105,
    "operating_margin": 0.057026743349571245,
    "net_margin": 0.047735845398438614
  },
  "analyst_recommendations": [
    {
      "index": 0,
      "period": "0m",
      "strongBuy": 2,
      "buy": 3,
      "hold": 9,
      "sell": 2,
      "strongSell": 2
    },
    {
      "index": 1,
      "period": "-1m",
      "strongBuy": 2,
      "buy": 3,
      "hold": 9,
      "sell": 2,
      "strongSell": 2
    },
    {
      "index": 2,
      "period": "-2m",
      "strongBuy": 3,
      "buy": 5,
      "hold": 7,
      "sell": 2,
      "strongSell": 1
    },
    {
      "index": 3,
      "period": "-3m",
      "strongBuy": 3,
      "buy": 5,
      "hold": 8,
      "sell": 2,
      "strongSell": 1
    }
  ],
  "news_headlines": [
    {
      "title": "",
      "link": "",
      "publisher": ""
    },
    {
      "title": "",
      "link": "",
      "publisher": ""
    },
    {
      "title": "",
      "link": "",
      "publisher": ""
    },
    {
      "title": "",
      "link": "",
      "publisher": ""
    },
    {
      "title": "",
      "link": "",
      "publisher": ""
    },
    {
      "title": "",
      "link": "",
      "publisher": ""
    },
    {
      "title": "",
      "link": "",
      "publisher": ""
    },
    {
      "title": "",
      "link": "",
      "publisher": ""
    },
    {
      "title": "",
      "link": "",
      "publisher": ""
    },
    {
      "title": "",
      "link": "",
      "publisher": ""
    }
  ],
  "fetched_at": "2026-04-19T03:45:57.459065"
}