{
  "ticker": "AIZ",
  "as_of_date": "2026-04-21",
  "close": 228.96,
  "sma_20": 220.6585,
  "sma_50": 221.4568,
  "sma_200": 217.358,
  "ema_20": 222.4607,
  "rsi_14": 70.9823,
  "macd_line": 1.6552,
  "macd_signal": 0.3756,
  "macd_histogram": 1.2796,
  "bb_upper": 229.2751,
  "bb_middle": 220.6585,
  "bb_lower": 212.0419,
  "bb_pct": 0.9817,
  "atr_14": 4.1527,
  "volume": 262419,
  "volume_sma_20": 280825.95,
  "volume_ratio": 0.9345,
  "high_52w": 245.3133,
  "low_52w": 178.941,
  "pct_from_52w_high": -0.0667,
  "pct_from_52w_low": 0.2795,
  "above_sma_20": true,
  "above_sma_50": true,
  "above_sma_200": true
}