{
  "ticker": "A",
  "as_of_date": "2026-04-21",
  "close": 122.09,
  "sma_20": 116.1274,
  "sma_50": 117.9782,
  "sma_200": 129.2589,
  "ema_20": 117.6036,
  "rsi_14": 69.1907,
  "macd_line": 1.101,
  "macd_signal": -0.0193,
  "macd_histogram": 1.1203,
  "bb_upper": 123.0541,
  "bb_middle": 116.1274,
  "bb_lower": 109.2008,
  "bb_pct": 0.9304,
  "atr_14": 3.1104,
  "volume": 1391705,
  "volume_sma_20": 1770025.25,
  "volume_ratio": 0.7863,
  "high_52w": 159.6199,
  "low_52w": 98.313,
  "pct_from_52w_high": -0.2351,
  "pct_from_52w_low": 0.2419,
  "above_sma_20": true,
  "above_sma_50": true,
  "above_sma_200": false
}