{
  "ticker": "CFG",
  "as_of_date": "2026-04-20",
  "close": 65.76,
  "sma_20": 61.8515,
  "sma_50": 61.5822,
  "sma_200": 55.0372,
  "ema_20": 62.6647,
  "rsi_14": 86.2249,
  "macd_line": 1.4939,
  "macd_signal": 1.0444,
  "macd_histogram": 0.4495,
  "bb_upper": 67.6272,
  "bb_middle": 61.8515,
  "bb_lower": 56.0758,
  "bb_pct": 0.8384,
  "atr_14": 1.5854,
  "volume": 3982450,
  "volume_sma_20": 4692092.5,
  "volume_ratio": 0.8488,
  "high_52w": 68.79,
  "low_52w": 32.7525,
  "pct_from_52w_high": -0.044,
  "pct_from_52w_low": 1.0078,
  "above_sma_20": true,
  "above_sma_50": true,
  "above_sma_200": true
}