{
  "ticker": "HOOD",
  "as_of_date": "2026-04-17",
  "close": 90.75,
  "sma_20": 73.0545,
  "sma_50": 75.5346,
  "sma_200": 107.3508,
  "ema_20": 76.4421,
  "rsi_14": 84.9788,
  "macd_line": 2.044,
  "macd_signal": -0.8119,
  "macd_histogram": 2.8559,
  "bb_upper": 87.3658,
  "bb_middle": 73.0545,
  "bb_lower": 58.7432,
  "bb_pct": 1.1182,
  "atr_14": 4.8092,
  "volume": 49681400,
  "volume_sma_20": 32461715.0,
  "volume_ratio": 1.5305,
  "high_52w": 153.86,
  "low_52w": 39.21,
  "pct_from_52w_high": -0.4102,
  "pct_from_52w_low": 1.3145,
  "above_sma_20": true,
  "above_sma_50": true,
  "above_sma_200": false
}