{
  "ticker": "TSCO",
  "as_of_date": "2026-04-17",
  "close": 45.01,
  "sma_20": 45.127,
  "sma_50": 48.8615,
  "sma_200": 53.6827,
  "ema_20": 45.6288,
  "rsi_14": 50.7246,
  "macd_line": -1.0166,
  "macd_signal": -1.2516,
  "macd_histogram": 0.2351,
  "bb_upper": 46.379,
  "bb_middle": 45.127,
  "bb_lower": 43.875,
  "bb_pct": 0.4533,
  "atr_14": 1.3121,
  "volume": 8807900,
  "volume_sma_20": 6125905.0,
  "volume_ratio": 1.4378,
  "high_52w": 63.1914,
  "low_52w": 43.23,
  "pct_from_52w_high": -0.2877,
  "pct_from_52w_low": 0.0412,
  "above_sma_20": false,
  "above_sma_50": false,
  "above_sma_200": false
}