{
  "ticker": "EQT",
  "as_of_date": "2026-04-17",
  "close": 58.48,
  "sma_20": 61.695,
  "sma_50": 60.9179,
  "sma_200": 55.8126,
  "ema_20": 60.2765,
  "rsi_14": 18.9171,
  "macd_line": -1.227,
  "macd_signal": -0.6295,
  "macd_histogram": -0.5975,
  "bb_upper": 69.0292,
  "bb_middle": 61.695,
  "bb_lower": 54.3608,
  "bb_pct": 0.2808,
  "atr_14": 2.0421,
  "volume": 10515600,
  "volume_sma_20": 8351970.0,
  "volume_ratio": 1.2591,
  "high_52w": 68.24,
  "low_52w": 46.5872,
  "pct_from_52w_high": -0.143,
  "pct_from_52w_low": 0.2553,
  "above_sma_20": false,
  "above_sma_50": false,
  "above_sma_200": true
}