{
  "info": {
    "symbol": "LIN",
    "name": "Linde plc",
    "sector": "Basic Materials",
    "industry": "Specialty Chemicals",
    "market": "US",
    "currency": "USD",
    "market_cap": 230839795712.0,
    "pe_ratio": 34.07319,
    "forward_pe": 25.54081,
    "dividend_yield": 1.3,
    "beta": 0.79,
    "fifty_two_week_high": 510.65,
    "fifty_two_week_low": 387.78
  },
  "financials": {
    "revenue": 33986000000.0,
    "net_income": 6898000000.0,
    "total_debt": 28069000000.0,
    "total_equity": 38245000000.0,
    "free_cash_flow": 5089000000.0,
    "gross_margin": 0.4883481433531454,
    "operating_margin": 0.2722885894191726,
    "net_margin": 0.20296592714647207
  },
  "analyst_recommendations": [
    {
      "index": 0,
      "period": "0m",
      "strongBuy": 4,
      "buy": 17,
      "hold": 4,
      "sell": 1,
      "strongSell": 1
    },
    {
      "index": 1,
      "period": "-1m",
      "strongBuy": 4,
      "buy": 17,
      "hold": 4,
      "sell": 1,
      "strongSell": 1
    },
    {
      "index": 2,
      "period": "-2m",
      "strongBuy": 3,
      "buy": 18,
      "hold": 5,
      "sell": 1,
      "strongSell": 1
    },
    {
      "index": 3,
      "period": "-3m",
      "strongBuy": 5,
      "buy": 18,
      "hold": 3,
      "sell": 1,
      "strongSell": 0
    }
  ],
  "news_headlines": [
    {
      "title": "",
      "link": "",
      "publisher": ""
    },
    {
      "title": "",
      "link": "",
      "publisher": ""
    },
    {
      "title": "",
      "link": "",
      "publisher": ""
    },
    {
      "title": "",
      "link": "",
      "publisher": ""
    },
    {
      "title": "",
      "link": "",
      "publisher": ""
    },
    {
      "title": "",
      "link": "",
      "publisher": ""
    },
    {
      "title": "",
      "link": "",
      "publisher": ""
    },
    {
      "title": "",
      "link": "",
      "publisher": ""
    },
    {
      "title": "",
      "link": "",
      "publisher": ""
    },
    {
      "title": "",
      "link": "",
      "publisher": ""
    }
  ],
  "fetched_at": "2026-04-20T23:16:43.510967"
}