{
  "ticker": "HD",
  "as_of_date": "2026-04-20",
  "close": 350.99,
  "sma_20": 333.34,
  "sma_50": 351.7463,
  "sma_200": 368.3527,
  "ema_20": 338.9269,
  "rsi_14": 68.3978,
  "macd_line": -0.2774,
  "macd_signal": -3.8893,
  "macd_histogram": 3.6119,
  "bb_upper": 351.2592,
  "bb_middle": 333.34,
  "bb_lower": 315.4208,
  "bb_pct": 0.9925,
  "atr_14": 9.1829,
  "volume": 3190830,
  "volume_sma_20": 3901026.5,
  "volume_ratio": 0.8179,
  "high_52w": 421.1917,
  "low_52w": 315.31,
  "pct_from_52w_high": -0.1667,
  "pct_from_52w_low": 0.1132,
  "above_sma_20": true,
  "above_sma_50": false,
  "above_sma_200": false
}