{
  "info": {
    "symbol": "BK",
    "name": "The Bank of New York Mellon Cor",
    "sector": "Financial Services",
    "industry": "Banks - Diversified",
    "market": "US",
    "currency": "USD",
    "market_cap": 93165289472.0,
    "pe_ratio": 16.774473,
    "forward_pe": 14.07856,
    "dividend_yield": 1.57,
    "beta": 1.053,
    "fifty_two_week_high": 137.54,
    "fifty_two_week_low": 73.55
  },
  "financials": {
    "revenue": 19759000000.0,
    "net_income": 5549000000.0,
    "total_debt": 34298000000.0,
    "total_equity": 44313000000.0,
    "free_cash_flow": 5177000000.0,
    "gross_margin": null,
    "operating_margin": null,
    "net_margin": 0.2808340503061896
  },
  "analyst_recommendations": [
    {
      "index": 0,
      "period": "0m",
      "strongBuy": 3,
      "buy": 6,
      "hold": 6,
      "sell": 0,
      "strongSell": 1
    },
    {
      "index": 1,
      "period": "-1m",
      "strongBuy": 3,
      "buy": 7,
      "hold": 6,
      "sell": 0,
      "strongSell": 1
    },
    {
      "index": 2,
      "period": "-2m",
      "strongBuy": 3,
      "buy": 7,
      "hold": 6,
      "sell": 0,
      "strongSell": 1
    },
    {
      "index": 3,
      "period": "-3m",
      "strongBuy": 4,
      "buy": 7,
      "hold": 5,
      "sell": 0,
      "strongSell": 1
    }
  ],
  "news_headlines": [
    {
      "title": "",
      "link": "",
      "publisher": ""
    },
    {
      "title": "",
      "link": "",
      "publisher": ""
    },
    {
      "title": "",
      "link": "",
      "publisher": ""
    },
    {
      "title": "",
      "link": "",
      "publisher": ""
    },
    {
      "title": "",
      "link": "",
      "publisher": ""
    },
    {
      "title": "",
      "link": "",
      "publisher": ""
    },
    {
      "title": "",
      "link": "",
      "publisher": ""
    },
    {
      "title": "",
      "link": "",
      "publisher": ""
    },
    {
      "title": "",
      "link": "",
      "publisher": ""
    },
    {
      "title": "",
      "link": "",
      "publisher": ""
    }
  ],
  "fetched_at": "2026-04-20T23:10:32.999608"
}