{
  "info": {
    "symbol": "CI",
    "name": "The Cigna Group",
    "sector": "Healthcare",
    "industry": "Healthcare Plans",
    "market": "US",
    "currency": "USD",
    "market_cap": 74773864448.0,
    "pe_ratio": 12.620379,
    "forward_pe": 8.37349,
    "dividend_yield": 2.24,
    "beta": 0.272,
    "fifty_two_week_high": 350.0,
    "fifty_two_week_low": 239.51
  },
  "financials": {
    "revenue": 274876000000.0,
    "net_income": 5957000000.0,
    "total_debt": 31463000000.0,
    "total_equity": 41713000000.0,
    "free_cash_flow": 8389000000.0,
    "gross_margin": null,
    "operating_margin": null,
    "net_margin": 0.02167159009880819
  },
  "analyst_recommendations": [
    {
      "index": 0,
      "period": "0m",
      "strongBuy": 6,
      "buy": 16,
      "hold": 2,
      "sell": 0,
      "strongSell": 0
    },
    {
      "index": 1,
      "period": "-1m",
      "strongBuy": 6,
      "buy": 16,
      "hold": 3,
      "sell": 0,
      "strongSell": 0
    },
    {
      "index": 2,
      "period": "-2m",
      "strongBuy": 6,
      "buy": 15,
      "hold": 4,
      "sell": 0,
      "strongSell": 0
    },
    {
      "index": 3,
      "period": "-3m",
      "strongBuy": 6,
      "buy": 15,
      "hold": 4,
      "sell": 0,
      "strongSell": 0
    }
  ],
  "news_headlines": [
    {
      "title": "",
      "link": "",
      "publisher": ""
    },
    {
      "title": "",
      "link": "",
      "publisher": ""
    },
    {
      "title": "",
      "link": "",
      "publisher": ""
    },
    {
      "title": "",
      "link": "",
      "publisher": ""
    },
    {
      "title": "",
      "link": "",
      "publisher": ""
    },
    {
      "title": "",
      "link": "",
      "publisher": ""
    },
    {
      "title": "",
      "link": "",
      "publisher": ""
    },
    {
      "title": "",
      "link": "",
      "publisher": ""
    },
    {
      "title": "",
      "link": "",
      "publisher": ""
    },
    {
      "title": "",
      "link": "",
      "publisher": ""
    }
  ],
  "fetched_at": "2026-04-20T23:11:28.740461"
}