{
  "ticker": "CI",
  "as_of_date": "2026-04-21",
  "close": 276.69,
  "sma_20": 271.8805,
  "sma_50": 275.2984,
  "sma_200": 280.6537,
  "ema_20": 273.4541,
  "rsi_14": 60.6515,
  "macd_line": 1.5403,
  "macd_signal": 0.516,
  "macd_histogram": 1.0243,
  "bb_upper": 283.57,
  "bb_middle": 271.8805,
  "bb_lower": 260.191,
  "bb_pct": 0.7057,
  "atr_14": 5.9229,
  "volume": 1470426,
  "volume_sma_20": 1417451.3,
  "volume_ratio": 1.0374,
  "high_52w": 342.7477,
  "low_52w": 236.8672,
  "pct_from_52w_high": -0.1927,
  "pct_from_52w_low": 0.1681,
  "above_sma_20": true,
  "above_sma_50": true,
  "above_sma_200": false
}